django_list_tests/__init__.py
django_list_tests/management/commands/list_tests.py
django_list_tests-0.1.2.dist-info/LICENSE
django_list_tests-0.1.2.dist-info/METADATA
django_list_tests-0.1.2.dist-info/WHEEL
django_list_tests-0.1.2.dist-info/top_level.txt
django_list_tests-0.1.2.dist-info/RECORD
